libresvip/__init__.py
libresvip/py.typed
libresvip/__pyinstaller/__init__.py
libresvip/__pyinstaller/hook-libresvip.py
libresvip/cli/__init__.py
libresvip/cli/__main__.py
libresvip/cli/app.py
libresvip/cli/prompt.py
libresvip/cli/commands/__init__.py
libresvip/cli/commands/conf.py
libresvip/cli/commands/plugin.py
libresvip/cli/commands/proj.py
libresvip/cli/commands/rpc.py
libresvip/cli/rpc/__init__.py
libresvip/cli/rpc/conversion_grpc.py
libresvip/cli/rpc/messages.py
libresvip/cli/rpc/server.py
libresvip/core/__init__.py
libresvip/core/compat.py
libresvip/core/config.py
libresvip/core/constants.py
libresvip/core/exceptions.py
libresvip/core/tick_counter.py
libresvip/core/time_interval.py
libresvip/core/time_sync.py
libresvip/core/warning_types.py
libresvip/core/lyric_phoneme/__init__.py
libresvip/core/lyric_phoneme/chinese/__init__.py
libresvip/core/lyric_phoneme/chinese/vocaloid_xsampa.py
libresvip/core/lyric_phoneme/japanese/__init__.py
libresvip/core/lyric_phoneme/japanese/vocaloid_xsampa.py
libresvip/core/lyric_phoneme/korean/__init__.py
libresvip/core/lyric_phoneme/korean/vocaloid_xsampa.py
libresvip/extension/__init__.py
libresvip/extension/base.py
libresvip/extension/manager.py
libresvip/extension/meta_info.py
libresvip/extension/vendor/__init__.py
libresvip/extension/vendor/pluginlib/__init__.py
libresvip/extension/vendor/pluginlib/_loader.py
libresvip/extension/vendor/pluginlib/_objects.py
libresvip/extension/vendor/pluginlib/_parent.py
libresvip/extension/vendor/pluginlib/_util.py
libresvip/extension/vendor/pluginlib/exceptions.py
libresvip/gui/__init__.py
libresvip/gui/__main__.py
libresvip/gui/models/__init__.py
libresvip/gui/models/base_task.py
libresvip/gui/models/list_models.py
libresvip/gui/models/table_models.py
libresvip/gui/modules/__init__.py
libresvip/gui/modules/application.py
libresvip/gui/modules/clipboard.py
libresvip/gui/modules/config_items.py
libresvip/gui/modules/font_loader.py
libresvip/gui/modules/frameless_window.py
libresvip-2.1.1.dist-info/METADATA
libresvip-2.1.1.dist-info/WHEEL
libresvip-2.1.1.dist-info/entry_points.txt
libresvip-2.1.1.dist-info/licenses/LICENSE
libresvip-2.1.1.dist-info/RECORD
